geocodio/__init__.py
geocodio/_version.py
geocodio/client.py
geocodio/distance.py
geocodio/exceptions.py
geocodio/models.py
geocodio_library_python-0.5.0.dist-info/METADATA
geocodio_library_python-0.5.0.dist-info/WHEEL
geocodio_library_python-0.5.0.dist-info/licenses/LICENSE
geocodio_library_python-0.5.0.dist-info/RECORD
